tssm/__init__.py
tssm/time_series_scaling_module.py
tssm/value_storage.py
tssm/calculation_models/__init__.py
tssm/calculation_models/average_calculation_model.py
tssm/calculation_models/calculation_base_class.py
tssm/calculation_models/maximum_class.py
tssm/calculation_models/normal_distribution_model.py
tssm/calculation_models/scaling_and_normal_distribution_model.py
tssm/calculation_models/scaling_profile_model.py
tssm/calculation_models/simultaneity_factor.py
tssm/calculation_models/profile_generation/__init__.py
tssm/calculation_models/profile_generation/bdew_electrical.py
tssm/calculation_models/profile_generation/bdew_heat.py
tssm/calculation_models/profile_generation/functions.py
tssm/calculation_models/profile_generation/hour_dict.py
tssm/gui/__init__.py
tssm/gui/create_translation_class.py
tssm/gui/data_2_tssm.py
tssm/gui/gui_structure.py
tssm/gui/start_gui.py
tssm/gui/translation_class.py
tssm/utils/BDEW_class.py
tssm/utils/BDEW_day.py
tssm/utils/__init__.py
tssm/utils/calc_indexes.py
tssm/utils/cast_2_same_sum.py
tssm/utils/cast_input_2_period.py
tssm/utils/create_bdew_electrical_data_class.py
tssm/utils/dict_casting.py
tssm/utils/errors.py
tssm/utils/period.py
tssm/utils/seasons.py
tssm-0.0.4.dist-info/LICENSE
tssm-0.0.4.dist-info/METADATA
tssm-0.0.4.dist-info/WHEEL
tssm-0.0.4.dist-info/top_level.txt
tssm-0.0.4.dist-info/RECORD
