Metadata-Version: 2.1
Name: tssm
Version: 0.0.4
Summary: Package to create out of a single load profile a profile for a whole district using the diversity factor
Home-page: https://git.fh-aachen.de/tb5152e/tssm
Author: Tobias Blanke & Dominik Fischer
License: BSD 3-Clause License
Keywords: load,simultaneity factor,scaling,load profile,time series
Platform: unix
Platform: linux
Platform: osx
Platform: win32
Platform: win64
Classifier: Programming Language :: Python :: 3.10
Classifier: Programming Language :: Python :: 3.8
Classifier: Programming Language :: Python :: 3.9
Classifier: Development Status :: 3 - Alpha
Classifier: License :: OSI Approved :: BSD License
Classifier: Intended Audience :: Science/Research
Classifier: Natural Language :: English
Classifier: Topic :: Scientific/Engineering :: Mathematics
Classifier: Topic :: Software Development :: Libraries :: Python Modules
Requires-Python: >=3.8
License-File: LICENSE
Requires-Dist: setuptools (>=63.2.0)
Requires-Dist: pandas (>=1.4.2)
Requires-Dist: numpy (>=1.22.4)
Requires-Dist: scipy (>=1.8.1)
Requires-Dist: levenshtein (>=0.20.8)
Requires-Dist: ScenarioGUI (>=0.2.0)
Requires-Dist: matplotlib (>=3.7.1)
Requires-Dist: detect-delimiter (>=0.1.1)
Provides-Extra: testing
Requires-Dist: flake8 (>=4.0.1) ; extra == 'testing'
Requires-Dist: tox (>=3.25) ; extra == 'testing'
Requires-Dist: pytest (>=7.0) ; extra == 'testing'
Requires-Dist: pytest-cov (>=3.0.0) ; extra == 'testing'
Requires-Dist: mypy (>=0.961) ; extra == 'testing'
Requires-Dist: pylint (>=2.14.5) ; extra == 'testing'
Requires-Dist: isort (>=5.10.1) ; extra == 'testing'
Requires-Dist: black (>=22.6.0) ; extra == 'testing'
